proto/CMakeLists.txt
proto/grpc_debugprobe.core
proto/pyocd_grpc/debugprobe.proto
pyocd_grpc/__init__.py
pyocd_grpc/_version.py
pyocd_grpc/debugprobe_pb2.py
pyocd_grpc/debugprobe_pb2.pyi
pyocd_grpc/debugprobe_pb2_grpc.py
pyocd_grpc/grpc_probe.py
pyocd_grpc/__pycache__/__init__.cpython-38.pyc
pyocd_grpc/__pycache__/_version.cpython-38.pyc
pyocd_grpc-0.2.6.dist-info/LICENSE
pyocd_grpc-0.2.6.dist-info/METADATA
pyocd_grpc-0.2.6.dist-info/WHEEL
pyocd_grpc-0.2.6.dist-info/entry_points.txt
pyocd_grpc-0.2.6.dist-info/top_level.txt
pyocd_grpc-0.2.6.dist-info/RECORD
