Metadata-Version: 2.1
Name: pyocd-grpc
Version: 0.2.6
Summary: a remote PyOCd debug probe plugin using gRPC
Author: Shareef Jalloq
Author-email: shareef.jalloq@idexbiometrics.com
Project-URL: homepage, https://github.com/idex-biometrics/pyocd-grpc
Classifier: Programming Language :: Python :: 3
Classifier: Programming Language :: Python :: 3.8
Classifier: Programming Language :: Python :: 3.9
Classifier: Programming Language :: Python :: 3.10
Classifier: Operating System :: MacOS :: MacOS X
Classifier: Operating System :: Microsoft :: Windows
Classifier: Operating System :: POSIX :: Linux
Classifier: Operating System :: POSIX :: BSD
Classifier: License :: OSI Approved :: BSD License
Classifier: Topic :: Scientific/Engineering
Classifier: Topic :: Software Development
Classifier: Topic :: Software Development :: Debuggers
Classifier: Topic :: Software Development :: Embedded Systems
Classifier: Topic :: System :: Hardware
Classifier: Topic :: Utilities
License-File: LICENSE
Requires-Dist: protobuf
Requires-Dist: grpcio
Requires-Dist: grpcio-tools
